airflow_provider_carbonaware/__init__.py
airflow_provider_carbonaware/example_dags/carbonaware.py
airflow_provider_carbonaware/example_dags/carbonaware_introspection.py
airflow_provider_carbonaware/operators/__init__.py
airflow_provider_carbonaware/operators/carbonaware.py
airflow_provider_carbonaware-0.2.1.dist-info/licenses/LICENSE
airflow_provider_carbonaware-0.2.1.dist-info/METADATA
airflow_provider_carbonaware-0.2.1.dist-info/WHEEL
airflow_provider_carbonaware-0.2.1.dist-info/entry_points.txt
airflow_provider_carbonaware-0.2.1.dist-info/top_level.txt
airflow_provider_carbonaware-0.2.1.dist-info/RECORD
