Metadata-Version: 2.4
Name: airflow-provider-carbonaware
Version: 0.2.1
Summary: An Apache Airflow provider package for CarbonAware.
Author-email: Ryan Singman <ryan@carbonaware.dev>
License: Apache License 2.0
Project-URL: Homepage, https://carbonaware.dev
Project-URL: Source, https://github.com/carbon-aware/airflow-provider-carbonaware/
Classifier: Framework :: Apache Airflow
Classifier: Framework :: Apache Airflow :: Provider
Requires-Python: >=3.9
License-File: LICENSE
Requires-Dist: apache-airflow>=2.4
Requires-Dist: carbonaware-scheduler-client>=0.1.2
Dynamic: license-file
